pythontextnow/__init__.py
pythontextnow/_version.py
pythontextnow/app.properties
pythontextnow/api/Client.py
pythontextnow/api/TextNowAPI.py
pythontextnow/api/__init__.py
pythontextnow/decorator/__init__.py
pythontextnow/decorator/cooldown.py
pythontextnow/enum/ContactType.py
pythontextnow/enum/MessageDirection.py
pythontextnow/enum/MessageType.py
pythontextnow/enum/ReadStatus.py
pythontextnow/enum/__init__.py
pythontextnow/exception/InvalidConversationException.py
pythontextnow/exception/__init__.py
pythontextnow/model/Avatar.py
pythontextnow/model/Group.py
pythontextnow/model/Member.py
pythontextnow/model/Message.py
pythontextnow/model/MultiMediaMessage.py
pythontextnow/model/TextMessage.py
pythontextnow/model/User.py
pythontextnow/model/__init__.py
pythontextnow/service/ConversationService.py
pythontextnow/service/__init__.py
pythontextnow/util/ConfigReader.py
pythontextnow/util/CustomFormatter.py
pythontextnow/util/CustomLogger.py
pythontextnow/util/__init__.py
pythontextnow/util/general.py
test/test_api/__init__.py
test/test_api/test_TextNowAPI.py
pythontextnow-1.1.0.dist-info/LICENSE
pythontextnow-1.1.0.dist-info/METADATA
pythontextnow-1.1.0.dist-info/WHEEL
pythontextnow-1.1.0.dist-info/top_level.txt
pythontextnow-1.1.0.dist-info/RECORD
