Metadata-Version: 2.1
Name: pythontextnow
Version: 1.1.0
Summary: A Python wrapper for TextNow.
Author: Joey Greco
Author-email: joeyagreco@gmail.com
License: MIT
License-File: LICENSE
Requires-Dist: requests
Requires-Dist: setuptools
Requires-Dist: phonenumbers
